MANIFEST.in
README
setup.py
bin/centersearch3
bin/installdronedeps3
bin/testpredictor3
bin/trigger3
distdrone3/__init__.py
distdrone3/text.py
distdrone3.egg-info/PKG-INFO
distdrone3.egg-info/SOURCES.txt
distdrone3.egg-info/dependency_links.txt
distdrone3.egg-info/not-zip-safe
distdrone3.egg-info/requires.txt
distdrone3.egg-info/top_level.txt
distdrone3/imgproc/__init__.py
distdrone3/imgproc/gentimedist.py
distdrone3/imgproc/imgproc.py
distdrone3/motion/__init__.py
distdrone3/motion/gears.py