Metadata-Version: 1.0
Name: distdrone3
Version: 0.0.1
Summary: package to drive parallel drone swarm
Home-page: https://github.com/isaacrob/distdrone3
Author: Isaac Robinson
Author-email: isaacrob@me.com
License: GNU
Keywords: drone,OpenCV,IPython,parallel
Platform: UNKNOWN
